driizzyyui/__init__.py
driizzyyui/core.py
driizzyyui/gui.py
driizzyyui/widgets.py
driizzyyui-0.1.0.dist-info/METADATA
driizzyyui-0.1.0.dist-info/WHEEL
driizzyyui-0.1.0.dist-info/top_level.txt
driizzyyui-0.1.0.dist-info/RECORD
