Metadata-Version: 2.4
Name: driizzyyui
Version: 0.1.0
Summary: A Discord selfbot client and GUI framework for Python, inspired by discord.py-self.
Author-email: DriizzyyB <driizzyyboosts@gmail.com>
License: MIT
Project-URL: Homepage, https://github.com/driizzyy
Project-URL: Repository, https://github.com/yourusername/driizzyyui
Keywords: discord,selfbot,gui,pyqt5
Requires-Python: >=3.8
Requires-Dist: httpx>=0.23.0
Requires-Dist: PyQt5>=5.15.0
